craftsmen/__init__.py
craftsmen/compose.py
craftsmen/identity.py
craftsmen/map.py
craftsmen/curry/curry.py
craftsmen/curry/placeholder.py
craftsmen-0.1.5.dist-info/LICENSE
craftsmen-0.1.5.dist-info/METADATA
craftsmen-0.1.5.dist-info/WHEEL
craftsmen-0.1.5.dist-info/top_level.txt
craftsmen-0.1.5.dist-info/RECORD
