Metadata-Version: 2.1
Name: craftsmen
Version: 0.1.5
Summary: craftsmen description
Home-page: https://github.com/heyderpd/pypi-craftsmen
Author: heyderpd
Author-email: heyderpd@gmail.com
License: MIT
Download-URL: https://github.com/heyderpd/pypi-craftsmen/dist/craftsmen-0.1.5.tar.gz
Keywords: ramda,utils,functional
Platform: any
Classifier: Development Status :: 3 - Alpha
Classifier: Intended Audience :: Developers
Classifier: Topic :: Software Development :: Build Tools
Classifier: License :: OSI Approved :: MIT License
Classifier: Programming Language :: Python :: 3
Classifier: Programming Language :: Python :: 3.8
